base_converter/__init__.py
base_converter/base_converter.py
base_converter_pedromagno-0.1.1.dist-info/METADATA
base_converter_pedromagno-0.1.1.dist-info/WHEEL
base_converter_pedromagno-0.1.1.dist-info/top_level.txt
base_converter_pedromagno-0.1.1.dist-info/RECORD
