Metadata-Version: 2.4
Name: base_converter_pedromagno
Version: 0.1.1
Summary: Base conversion library (base 2 to 16) with decimal and fractional support.
Home-page: https://github.com/PedroMagno11/base_converter
Author: Pedro Magno
Author-email: pedromagnopro@gmail.com
Classifier: Programming Language :: Python :: 3
Classifier: Operating System :: OS Independent
Requires-Python: >=3.6
Dynamic: author
Dynamic: author-email
Dynamic: classifier
Dynamic: description
Dynamic: description-content-type
Dynamic: home-page
Dynamic: requires-python
Dynamic: summary
